k2connect/__init__.py
k2connect/attribute.py
k2connect/authorization.py
k2connect/exceptions.py
k2connect/json_builder.py
k2connect/k2_model.py
k2connect/k2_requests.py
k2connect/notifications.py
k2connect/pay.py
k2connect/payload_decomposer.py
k2connect/polling.py
k2connect/receive_payments.py
k2connect/result_processor.py
k2connect/service.py
k2connect/transfers.py
k2connect/validation.py
k2connect/webhooks.py
k2_connect-1.2.7.dist-info/METADATA
k2_connect-1.2.7.dist-info/WHEEL
k2_connect-1.2.7.dist-info/top_level.txt
k2_connect-1.2.7.dist-info/RECORD
