Metadata-Version: 2.4
Name: k2-connect
Version: 1.2.7
Summary: A python SDK to connect to Kopo Kopo API
Home-page: https://github.com/kopokopo/k2-connect-python
Author: Philip Wafula, David Mwangi
Author-email: philipwafula2@gmail.com, david.mwangi@kopokopo.com
License: MIT
Classifier: Development Status :: 5 - Production/Stable
Classifier: Intended Audience :: Developers
Classifier: Programming Language :: Python :: 3
Classifier: License :: OSI Approved :: MIT License
Classifier: Operating System :: OS Independent
Requires-Python: >=3
Requires-Dist: flask~=3.1.0
Requires-Dist: requests~=2.32.3
Requires-Dist: urlvalidator~=0.1
Requires-Dist: pip~=24.3.1
Requires-Dist: wheel>=0.45.1
Requires-Dist: setuptools>=75.6.0
Dynamic: author
Dynamic: author-email
Dynamic: classifier
Dynamic: description
Dynamic: description-content-type
Dynamic: home-page
Dynamic: license
Dynamic: requires-dist
Dynamic: requires-python
Dynamic: summary
